{
  "schema_version": "1.0",
  "normalizer_version": "0.2.0",
  "source": {
    "procedure_code": "1.115321",
    "title": "Thu hồi, hủy Giấy chứng nhận đã cấp và cấp Giấy chứng nhận quyền sử dụng đất, quyền sở hữu tài sản gắn liền với đất sau khi thu hồi Giấy chứng nhận đã cấp",
    "raw_structured_parser_version": "0.1.0",
    "field": "Đất đai"
  },
  "procedure": {
    "level": "Cấp xã",
    "procedure_type": "TTHC được luật giao quy định chi tiết",
    "target_users": [
      "Doanh nghiệp Việt Nam",
      "Doanh nghiệp có vốn đầu tư nước ngoài",
      "Tổ chức (không bao gồm doanh nghiệp",
      "HTX)",
      "Người Việt Nam định cư ở nước ngoài",
      "Công dân Việt Nam",
      "Doanh nghiệp",
      "Tổ chức nước ngoài",
      "Hợp tác xã"
    ],
    "authorities": [],
    "receiving_places": []
  },
  "submission": {
    "channels": [
      "in_person",
      "online",
      "postal"
    ],
    "methods": [
      {
        "method_id": "method_1",
        "channel": "in_person",
        "processing_time_text": "45 ngày làm việc",
        "fee_text": null,
        "description": "- Thời gian thu hồi Giấy chứng nhận đã cấp không quá 25 ngày làm việc. <br>- Thời gian thực hiện đăng ký, cấp lại Giấy chứng nhận sau thu hồi không quá 20 ngày làm việc (trong đó đăng ký đất đai, tài sản gắn liền với đất lần đầu là không quá 17 ngày làm việc; cấp Giấy chứng nhận là không quá 03 ngày làm việc) đối với trường hợp thu hồi Giấy chứng nhận đã cấp lần đầu. Đối với các xã miền núi, hải đảo, vùng sâu, vùng xa, vùng có điều kiện kinh tế - xã hội khó khăn, vùng có điều kiện kinh tế - xã hội đặc biệt khó khăn thì thời gian thực hiện thu hồi Giấy chứng nhận đã cấp là không quá 35 ngày làm việc, thời gian cấp lại Giấy chứng nhận sau thu hồi là không quá 30 ngày làm việc.",
        "is_online": false,
        "is_postal": false,
        "is_in_person": true
      },
      {
        "method_id": "method_2",
        "channel": "online",
        "processing_time_text": "45 ngày làm việc",
        "fee_text": null,
        "description": "- Thời gian thu hồi Giấy chứng nhận đã cấp không quá 25 ngày làm việc. <br>- Thời gian thực hiện đăng ký, cấp lại Giấy chứng nhận sau thu hồi không quá 20 ngày làm việc (trong đó đăng ký đất đai, tài sản gắn liền với đất lần đầu là không quá 17 ngày làm việc; cấp Giấy chứng nhận là không quá 03 ngày làm việc) đối với trường hợp thu hồi Giấy chứng nhận đã cấp lần đầu. Đối với các xã miền núi, hải đảo, vùng sâu, vùng xa, vùng có điều kiện kinh tế - xã hội khó khăn, vùng có điều kiện kinh tế - xã hội đặc biệt khó khăn thì thời gian thực hiện thu hồi Giấy chứng nhận đã cấp là không quá 35 ngày làm việc, thời gian cấp lại Giấy chứng nhận sau thu hồi là không quá 30 ngày làm việc.",
        "is_online": true,
        "is_postal": false,
        "is_in_person": false
      },
      {
        "method_id": "method_3",
        "channel": "postal",
        "processing_time_text": "45 ngày làm việc",
        "fee_text": null,
        "description": "- Thời gian thu hồi Giấy chứng nhận đã cấp không quá 25 ngày làm việc. <br>- Thời gian thực hiện đăng ký, cấp lại Giấy chứng nhận sau thu hồi không quá 20 ngày làm việc (trong đó đăng ký đất đai, tài sản gắn liền với đất lần đầu là không quá 17 ngày làm việc; cấp Giấy chứng nhận là không quá 03 ngày làm việc) đối với trường hợp thu hồi Giấy chứng nhận đã cấp lần đầu. Đối với các xã miền núi, hải đảo, vùng sâu, vùng xa, vùng có điều kiện kinh tế - xã hội khó khăn, vùng có điều kiện kinh tế - xã hội đặc biệt khó khăn thì thời gian thực hiện thu hồi Giấy chứng nhận đã cấp là không quá 35 ngày làm việc, thời gian cấp lại Giấy chứng nhận sau thu hồi là không quá 30 ngày làm việc.",
        "is_online": false,
        "is_postal": true,
        "is_in_person": false
      }
    ],
    "timing_summary": {
      "unique_processing_times": [
        "45 ngày làm việc"
      ],
      "method_count": 3
    }
  },
  "documents": {
    "required": [
      {
        "document_id": "gi_y_ch_ng_nh_n_quy_n_s_d_ng_t_quy_n_s_h_u_t_i_s_n_g_n_li_n_v_i_t",
        "name": "Giấy chứng nhận quyền sử dụng đất, quyền sở hữu tài sản gắn liền với đất",
        "group_name": "default",
        "group_type": "unknown",
        "original_count": "1",
        "copy_count": "0",
        "conditions": [],
        "attachment_label": null,
        "attachment_path": null
      }
    ],
    "conditional": [
      {
        "document_id": "v_n_b_n_v_vi_c_i_di_n_theo_quy_nh_c_a_ph_p_lu_t_v_d_n_s_i_v_i_tr_ng_h_p_th_c_hi_n_th_t_c_ng_k_t_ai_t_i_s_n_g_n_li_n_v_i_t_th_ng_qua_ng_i_i_di_n",
        "name": "Văn bản về việc đại diện theo quy định của pháp luật về dân sự đối với trường hợp thực hiện thủ tục đăng ký đất đai, tài sản gắn liền với đất thông qua người đại diện",
        "group_name": "default",
        "group_type": "unknown",
        "original_count": "1",
        "copy_count": "0",
        "conditions": [
          "Văn bản về việc đại diện theo quy định của pháp luật về dân sự đối với trường hợp thực hiện thủ tục đăng ký đất đai, tài sản gắn liền với đất thông qua người đại diện"
        ],
        "attachment_label": null,
        "attachment_path": null
      }
    ],
    "presented": [],
    "notes": [],
    "forms": [],
    "empty_groups": [],
    "document_count": 2
  },
  "process": {
    "steps": [
      {
        "step_id": "step_1",
        "title": null,
        "content": "1.",
        "actor": "user",
        "channel_hint": null,
        "time_hint": null
      },
      {
        "step_id": "step_2",
        "title": "Bước 1:",
        "content": "Bước 1: Người yêu cầu nộp hồ sơ đến Bộ phận Một cửa.",
        "actor": "user",
        "channel_hint": null,
        "time_hint": null
      },
      {
        "step_id": "step_3",
        "title": "Bước 2:",
        "content": "Bước 2: Cơ quan tiếp nhận hồ sơ có trách nhiệm: - Kiểm tra tính đầy đủ của thành phần hồ sơ và cấp Giấy tiếp nhận hồ sơ và hẹn trả kết quả. Trường hợp chưa đầy đủ thành phần hồ sơ thì trả hồ sơ kèm Phiếu yêu cầu bổ sung, hoàn thiện hồ sơ để người yêu cầu đăng ký hoàn thiện, bổ sung theo quy định. - Chuyển hồ sơ đến Ủy ban nhân dân cấp xã nơi có đất.",
        "actor": "authority",
        "channel_hint": null,
        "time_hint": null
      },
      {
        "step_id": "step_4",
        "title": "Bước 3:",
        "content": "Bước 3: Cơ quan có chức năng quản lý đất đai cấp xã thực hiện: - Thông báo cho Văn phòng đăng ký đất đai, Chi nhánh Văn phòng đăng ký đất đai chuyển hồ sơ cấp Giấy chứng nhận lần đầu để kiểm tra, xem xét và trình Chủ tịch Ủy ban nhân dân cấp xã quyết định thu hồi Giấy chứng nhận đã cấp không đúng quy định của pháp luật đất đai. - Kiểm tra hồ sơ, xác định lại thông tin quy định tại điểm d khoản 2 Điều 152 Luật Đất đai theo đúng quy định của pháp luật đất đai tại thời điểm cấp Giấy chứng nhận. - Trình Chủ tịch Ủy ban nhân dân cấp xã cấp Giấy chứng nhận. - Chuyển hồ sơ đã giải quyết đến Văn phòng đăng ký đất đai, Chi nhánh Văn phòng đăng ký đất đai để thực hiện chỉnh lý hồ sơ địa chính, cơ sở dữ liệu đất đai; chuyển Giấy chứng nhận đến cơ quan tiếp nhận hồ sơ để trao cho người được cấp.",
        "actor": "authority",
        "channel_hint": null,
        "time_hint": null
      }
    ],
    "step_count": 4,
    "notes": []
  },
  "eligibility": {
    "conditions": [],
    "has_conditions": false
  },
  "results": {
    "items": [
      {
        "name": "Giấy chứng nhận quyền sử dụng đất, quyền sở hữu tài sản gắn liền với đất",
        "result_code": "H15-KQ000200",
        "raw_text": "Giấy chứng nhận quyền sử dụng đất, quyền sở hữu tài sản gắn liền với đất"
      },
      {
        "name": "Quyết định thu hồi Giấy chứng nhận đã cấp sai quy định của pháp luật",
        "result_code": "H15-KQ000302",
        "raw_text": "Quyết định thu hồi Giấy chứng nhận đã cấp sai quy định của pháp luật"
      }
    ],
    "primary_result": {
      "name": "Giấy chứng nhận quyền sử dụng đất, quyền sở hữu tài sản gắn liền với đất",
      "result_code": "H15-KQ000200",
      "raw_text": "Giấy chứng nhận quyền sử dụng đất, quyền sở hữu tài sản gắn liền với đất"
    }
  },
  "legal_basis": {
    "items": [
      {
        "title": "Nghị định 102/2024/NĐ-CP ngày 30/7/2024 của Chính phủ quy định chi tiết thi hành một số điều của Luật Đất đai.",
        "code": "102/2024/NĐ-CP"
      },
      {
        "title": "Quy định về phân định thẩm quyền của chính quyền địa phương 02 cấp, phân quyền, phân cấp trong lĩnh vực đất đai",
        "code": "151/2025/NĐ-CP"
      },
      {
        "title": "Nghị định số 118/2025/NĐ-CP của Chính phủ: Về thực hiện thủ tục hành chính theo cơ chế một cửa, một cửa liên thông tại Bộ phận Một cửa và Cổng Dịch vụ công quốc gia",
        "code": "118/2025/NĐ-CP"
      },
      {
        "title": "quy định chi tiết và hướng dẫn một số điều của Nghị quyết số 254/2025/QH15 của Quốc hội quy định một số cơ chế, chính sách tháo gỡ khó khăn vướng mắc trong tổ chức thi hành Luật Đất đai",
        "code": "49/2026/NĐ-CP"
      },
      {
        "title": "Quy định trình tự, thủ tục hành chính trong lĩnh vực đất đai trên địa bàn tỉnh Đắk Lắk.",
        "code": "57/2026/QĐ-UBND"
      },
      {
        "title": "Nghị định quy định về điều tra cơ bản đất đai, đăng ký, cấp Giấy chứng nhận quyền sử dụng đất, quyền sở hữu tài sản gắn liền với đất và Hệ thống thông tin đất đai.",
        "code": "101/2024/NĐ-CP"
      },
      {
        "title": "Luật Đất đai số 31/2024/QH15 ngày 18/01/2024 được sửa đổi bổ sung một số điều bởi Luật số 43/2024/QH15, Luật số 47/2024/QH15 và Luật số 58/2024/QH15 của Quốc hội.",
        "code": "31/2024/QH15"
      },
      {
        "title": "Sửa đổi, bổ sung một số điều của các nghị định quy định chi tiết thi hành Luật Đất đai",
        "code": "226/2025/NĐ-CP"
      }
    ],
    "count": 8
  },
  "attachments": [],
  "signals": {
    "raw_parse_warnings": [],
    "missing_documents": false,
    "documents_section_present": true,
    "documents_declared_empty": false,
    "documents_only_in_notes": false,
    "missing_results": false
  }
}